VBPatcher/__init__.py
VBPatcher/main.py
VBPatcher/appglobals/__init__.py
VBPatcher/appglobals/appglobals.py
VBPatcher/appglobals/globals.py
VBPatcher/applogger/__init__.py
VBPatcher/applogger/applogger.py
VBPatcher/apploggers/__init__.py
VBPatcher/apploggers/loggers.py
VBPatcher/downloader/__init__.py
VBPatcher/downloader/downloader.py
VBPatcher/logs/.gitkeep
VBPatcher/patch-files/development/.gitkeep
VBPatcher/patch-files/stable/.gitkeep
VBPatcher/patching/__init__.py
VBPatcher/patching/patching.py
VBPatcher/subprocessing/__init__.py
VBPatcher/subprocessing/subprocessing.py
VBPatcher/validation/__init__.py
VBPatcher/validation/validation.py
VBPatcher-0.9.0.dist-info/LICENSE
VBPatcher-0.9.0.dist-info/METADATA
VBPatcher-0.9.0.dist-info/WHEEL
VBPatcher-0.9.0.dist-info/entry_points.txt
VBPatcher-0.9.0.dist-info/top_level.txt
VBPatcher-0.9.0.dist-info/RECORD
