Metadata-Version: 2.1
Name: VBPatcher
Version: 0.9.0
Summary: The Valheim BepInEx Patcher (VBPatcher) is a CLI application for patching the Unity modding plugin, BepInEx, to its latest release (whether stable or bleeding-edge).
Home-page: https://github.com/schlopp96/VBPatcher
Author: schlopp96
Author-email: schloppdaddy@gmail.com
License: GPL v3.0
Keywords: python,Valheim,BepInEx,patcher,mods,nexus,vbp,stable,bleeding,edge,VBPatcher,vortex,patching,patch-install,CLI,console
Classifier: Development Status :: 3 - Alpha
Classifier: Environment :: Console
Classifier: Intended Audience :: End Users/Desktop
Classifier: License :: OSI Approved :: GNU General Public License v3 or later (GPLv3+)
Classifier: Natural Language :: English
Classifier: Operating System :: Microsoft :: Windows
Classifier: Programming Language :: Python :: 3
Classifier: Programming Language :: Python :: 3.6
Classifier: Programming Language :: Python :: 3.7
Classifier: Programming Language :: Python :: 3.8
Classifier: Programming Language :: Python :: 3.9
Classifier: Programming Language :: Python :: 3.10
Classifier: Programming Language :: Python :: 3.11
Classifier: Topic :: Games/Entertainment
Classifier: Topic :: Utilities
License-File: LICENSE
Requires-Dist: beautifulsoup4 (==4.11.1)
Requires-Dist: PyLoadBar (==0.2.0)
Requires-Dist: setuptools (>=58.1.0)
Requires-Dist: tqdm (==4.64.0)
